__init__.py
z.py
HattusaProcessor/__init__.py
HattusaProcessor/main.py
HattusaProcessor/src/__init__.py
HattusaProcessor/src/example/__init__.py
HattusaProcessor/src/service/__init__.py
HattusaProcessor/src/service/hattusa_service.py
HattusaProcessor/src/service/utils/__init__.py
HattusaProcessor/src/service/utils/configurator.py
HattusaProcessor/src/service/utils/generator_utils.py
HattusaProcessor/src/service/utils/hscheduler.py
HattusaProcessor/src/service/utils/redis_utils.py
HattusaProcessor/src/service/utils/s3_utils.py
hattusaservice-0.0.1.dist-info/METADATA
hattusaservice-0.0.1.dist-info/WHEEL
hattusaservice-0.0.1.dist-info/RECORD
