Metadata-Version: 2.1
Name: hattusaservice
Version: 0.0.1
Summary: Hattusa Processor First Build
Author-email: Mustafa Yilmaz <mustafa.yilmaz@spp42.com>
Classifier: License :: OSI Approved :: MIT License
Classifier: Operating System :: OS Independent
Classifier: Programming Language :: Python :: 3
Requires-Python: >=3.7
Requires-Dist: apscheduler==3.10.4
Requires-Dist: boto3==1.24.59
Requires-Dist: orjson==3.9.9
Requires-Dist: pytz==2023.3.post1
Requires-Dist: reactivex==4.0.4
Requires-Dist: redis==5.0.1
Requires-Dist: s3fs==2023.3.0
Requires-Dist: shortuuid==1.0.11
